Workbook

Sheet Instruções
A1: PLANILHA DE FLUXO DE CAIXA — PEQUENOS NEGÓCIOS
A2: Atividade Extensionista — Gestão de Fluxo de Caixa Para Pequenos Negócios Locais
A4: ABA | B4: DESCRIÇÃO | C4: COMO USAR
A5: Fluxo Mensal | B5: Controle mês a mês das entradas e saídas com totais automáticos | C5: Preencha as células azuis com seus valores mensais
A6: DRE Simplificada | B6: Demonstração de Resultado do Exercício — visão anual do lucro/prejuízo | C6: Automático — alimentado pelo Fluxo Mensal
A7: Projeção 12 Meses | B7: Projeção futura com taxa de crescimento configurável | C7: Defina a taxa de crescimento na célula azul indicada
A8: Painel Resumo | B8: Dashboard visual com indicadores e gráfico de evolução do caixa | C8: Apenas leitura — gerado automaticamente
A9: Instruções | B9: Esta aba — guia de uso da planilha | C9: —
A11: 💡 LEGENDA DAS CORES
A12: ■ | B12: Azul — células de INPUT: preencha com seus dados
A13: ■ | B13: Amarelo — células de destaque / premissas importantes
A14: ■ | B14: Verde claro — fórmulas automáticas (não edite)
A15: ■ | B15: Vermelho — resultado negativo (atenção!)

Sheet Fluxo Mensal
A1: FLUXO DE CAIXA — CONTROLE MENSAL
A2: Empresa / Negócio:
B4: CATEGORIAS | C4: Jan | D4: Fev | E4: Mar | F4: Abr | G4: Mai | H4: Jun | I4: Jul | J4: Ago | K4: Set | L4: Out | M4: Nov | N4: Dez | O4: TOTAL ANUAL
B6: Vendas à Vista | O6: =SUM(C6:N6) -> 0
B7: Vendas a Prazo Recebidas | O7: =SUM(C7:N7) -> 0
B8: Prestação de Serviços | O8: =SUM(C8:N8) -> 0
B9: Outras Receitas | O9: =SUM(C9:N9) -> 0
B10: TOTAL ENTRADAS | C10: =C6+C7+C8+C9 -> 0 | D10: =D6+D7+D8+D9 -> 0 | E10: =E6+E7+E8+E9 -> 0 | F10: =F6+F7+F8+F9 -> 0 | G10: =G6+G7+G8+G9 -> 0 | H10: =H6+H7+H8+H9 -> 0 | I10: =I6+I7+I8+I9 -> 0 | J10: =J6+J7+J8+J9 -> 0 | ... O10: =O6+O7+O8+O9 -> 0
B13: Aluguel / Condomínio | O13: =SUM(C13:N13) -> 0
B14: Salários e Pró-labore | O14: =SUM(C14:N14) -> 0
B15: Energia Elétrica | O15: =SUM(C15:N15) -> 0
B16: Internet e Telefone | O16: =SUM(C16:N16) -> 0
B17: Contador / Honorários | O17: =SUM(C17:N17) -> 0
B18: SUBTOTAL SAÍDAS FIXAS | C18: =C13+C14+C15+C16+C17 -> 0 | D18: =D13+D14+D15+D16+D17 -> 0 | E18: =E13+E14+E15+E16+E17 -> 0 | F18: =F13+F14+F15+F16+F17 -> 0 | G18: =G13+G14+G15+G16+G17 -> 0 | H18: =H13+H14+H15+H16+H17 -> 0 | I18: =I13+I14+I15+I16+I17 -> 0 | J18: =J13+J14+J15+J16+J17 -> 0 | ... O18: =O13+O14+O15+O16+O17 -> 0
B21: Compra de Mercadorias / Estoque | O21: =SUM(C21:N21) -> 0
B22: Frete e Logística | O22: =SUM(C22:N22) -> 0
B23: Marketing e Publicidade | O23: =SUM(C23:N23) -> 0
B24: Manutenção e Reparos | O24: =SUM(C24:N24) -> 0
B25: Outros Gastos Variáveis | O25: =SUM(C25:N25) -> 0
B26: SUBTOTAL SAÍDAS VARIÁVEIS | C26: =C21+C22+C23+C24+C25 -> 0 | D26: =D21+D22+D23+D24+D25 -> 0 | E26: =E21+E22+E23+E24+E25 -> 0 | F26: =F21+F22+F23+F24+F25 -> 0 | G26: =G21+G22+G23+G24+G25 -> 0 | H26: =H21+H22+H23+H24+H25 -> 0 | I26: =I21+I22+I23+I24+I25 -> 0 | J26: =J21+J22+J23+J24+J25 -> 0 | ... O26: =O21+O22+O23+O24+O25 -> 0
B29: DAS / Simples Nacional | O29: =SUM(C29:N29) -> 0
B30: Outras Taxas | O30: =SUM(C30:N30) -> 0
B31: SUBTOTAL IMPOSTOS | C31: =C29+C30 -> 0 | D31: =D29+D30 -> 0 | E31: =E29+E30 -> 0 | F31: =F29+F30 -> 0 | G31: =G29+G30 -> 0 | H31: =H29+H30 -> 0 | I31: =I29+I30 -> 0 | J31: =J29+J30 -> 0 | ... O31: =O29+O30 -> 0
B33: TOTAL SAÍDAS | C33: =C18+C26+C31 -> 0 | D33: =D18+D26+D31 -> 0 | E33: =E18+E26+E31 -> 0 | F33: =F18+F26+F31 -> 0 | G33: =G18+G26+G31 -> 0 | H33: =H18+H26+H31 -> 0 | I33: =I18+I26+I31 -> 0 | J33: =J18+J26+J31 -> 0 | ... O33: =O18+O26+O31 -> 0
B35: 💰 SALDO DO PERÍODO | C35: =C10-C33 -> 0 | D35: =D10-D33 -> 0 | E35: =E10-E33 -> 0 | F35: =F10-F33 -> 0 | G35: =G10-G33 -> 0 | H35: =H10-H33 -> 0 | I35: =I10-I33 -> 0 | J35: =J10-J33 -> 0 | ... O35: =O10-O33 -> 0
B36: 🏦 SALDO ACUMULADO | C36: =C35 -> 0 | D36: =C36+D35 -> 0 | E36: =D36+E35 -> 0 | F36: =E36+F35 -> 0 | G36: =F36+G35 -> 0 | H36: =G36+H35 -> 0 | I36: =H36+I35 -> 0 | J36: =I36+J35 -> 0 | K36: =J36+K35 -> 0 | ... N36: =M36+N35 -> 0 | O36: =N36 -> 0
A38: 📌 Células AZUIS = preencha com seus dados reais | Células VERDES = calculadas automaticamente | Linha AMARELA = saldo acumulado do ano

Sheet DRE Simplificada
A1: DRE — DEMONSTRAÇÃO DO RESULTADO DO EXERCÍCIO
A2: Alimentado automaticamente pela aba Fluxo Mensal
B4: DEMONSTRAÇÃO DO RESULTADO — ANUAL | D4: % da Receita
B5: Receita Bruta Total | C5: ='Fluxo Mensal'!O10 -> 0
B6: Total de Despesas Pagas | C6: ='Fluxo Mensal'!O33 -> 0
B7: Resultado Bruto | C7: =C5-C6 -> 0 | D7: =IFERROR(C7/C5,0) -> 0
B9: Saídas Fixas | C9: ='Fluxo Mensal'!O18 -> 0 | D9: =IFERROR(C10/C5,0) -> 0
B10: Saídas Variáveis | C10: ='Fluxo Mensal'!O26 -> 0 | D10: =IFERROR(C11/C5,0) -> 0
B11: Impostos e Taxas | C11: ='Fluxo Mensal'!O31 -> 0 | D11: =IFERROR(C12/C5,0) -> 0
B13: LUCRO / PREJUÍZO LÍQUIDO | C13: ='Fluxo Mensal'!O35 -> 0 | D13: =IFERROR(C15/C5,0) -> 0
B14: SALDO ACUMULADO FINAL | C14: ='Fluxo Mensal'!N36 -> 0

Sheet Projeção 12 Meses
A1: PROJEÇÃO DE FLUXO DE CAIXA — PRÓXIMOS 12 MESES
B2: Taxa de crescimento mensal estimada: | C2: 0.03 | D2: ← Altere aqui a taxa de crescimento esperada
B3: CATEGORIAS | C3: Mês 1 | D3: Mês 2 | E3: Mês 3 | F3: Mês 4 | G3: Mês 5 | H3: Mês 6 | I3: Mês 7 | J3: Mês 8 | K3: Mês 9 | L3: Mês 10 | M3: Mês 11 | N3: Mês 12 | O3: TOTAL
B4: Receita Projetada | C4: =('Fluxo Mensal'!O10/12)*(1+$C$2)^0 -> 0 | D4: =('Fluxo Mensal'!O10/12)*(1+$C$2)^1 -> 0 | E4: =('Fluxo Mensal'!O10/12)*(1+$C$2)^2 -> 0 | F4: =('Fluxo Mensal'!O10/12)*(1+$C$2)^3 -> 0 | G4: =('Fluxo Mensal'!O10/12)*(1+$C$2)^4 -> 0 | H4: =('Fluxo Mensal'!O10/12)*(1+$C$2)^5 -> 0 | I4: =('Fluxo Mensal'!O10/12)*(1+$C$2)^6 -> 0 | J4: =('Fluxo Mensal'!O10/12)*(1+$C$2)^7 -> 0 | K4: =('Fluxo Mensal'!O10/12)*(1+$C$2)^8 -> 0 | L4: =('Fluxo Mensal'!O10/12)*(1+$C$2)^9 -> 0 | M4: =('Fluxo Mensal'!O10/12)*(1+$C$2)^10 -> 0 | N4: =('Fluxo Mensal'!O10/12)*(1+$C$2)^11 -> 0 | O4: =SUM(C4:N4) -> 0
B5: Despesas Projetadas | C5: =('Fluxo Mensal'!O33/12)*(1+$C$2)^0 -> 0 | D5: =('Fluxo Mensal'!O33/12)*(1+$C$2)^1 -> 0 | E5: =('Fluxo Mensal'!O33/12)*(1+$C$2)^2 -> 0 | F5: =('Fluxo Mensal'!O33/12)*(1+$C$2)^3 -> 0 | G5: =('Fluxo Mensal'!O33/12)*(1+$C$2)^4 -> 0 | H5: =('Fluxo Mensal'!O33/12)*(1+$C$2)^5 -> 0 | I5: =('Fluxo Mensal'!O33/12)*(1+$C$2)^6 -> 0 | J5: =('Fluxo Mensal'!O33/12)*(1+$C$2)^7 -> 0 | K5: =('Fluxo Mensal'!O33/12)*(1+$C$2)^8 -> 0 | L5: =('Fluxo Mensal'!O33/12)*(1+$C$2)^9 -> 0 | M5: =('Fluxo Mensal'!O33/12)*(1+$C$2)^10 -> 0 | N5: =('Fluxo Mensal'!O33/12)*(1+$C$2)^11 -> 0 | O5: =SUM(C5:N5) -> 0
B6: Saldo Projetado | C6: =C4-C5 -> 0 | D6: =D4-D5 -> 0 | E6: =E4-E5 -> 0 | F6: =F4-F5 -> 0 | G6: =G4-G5 -> 0 | H6: =H4-H5 -> 0 | I6: =I4-I5 -> 0 | J6: =J4-J5 -> 0 | ... N6: =N4-N5 -> 0 | O6: =SUM(C6:N6) -> 0
B7: Saldo Acumulado | C7: =C6 -> 0 | D7: =C7+D6 -> 0 | E7: =D7+E6 -> 0 | F7: =E7+F6 -> 0 | G7: =F7+G6 -> 0 | H7: =G7+H6 -> 0 | I7: =H7+I6 -> 0 | J7: =I7+J6 -> 0 | K7: =J7+K6 -> 0 | ... N7: =M7+N6 -> 0 | O7: =SUM(C7:N7) -> 0
B9: ⚠️ Esta projeção usa médias do período atual. Ajuste a taxa de crescimento conforme a realidade do seu negócio.

Sheet Painel Resumo
A1: PAINEL RESUMO DO NEGÓCIO
A2: KPI | B2: VALOR
A3: 💰 Receita Total Anual | B3: ='Fluxo Mensal'!O10 -> 0
A4: 📤 Total Despesas | B4: ='Fluxo Mensal'!O33 -> 0
A5: 📊 Resultado (Lucro/Prejuízo) | B5: ='Fluxo Mensal'!O35 -> 0
A6: 🏦 Saldo Acumulado Final | B6: ='Fluxo Mensal'!N36 -> 0
A7: 📈 Margem de Resultado | B7: =IF('Fluxo Mensal'!O10=0,0,'Fluxo Mensal'!O35/'Fluxo Mensal'!O10) -> 0
A9: 📌 Painel atualizado automaticamente com os dados do Fluxo Mensal
